{
  "trainingPhrases": [ {
    "parts": [ {
      "text": "glass bottles",
      "parameterId": "trash"
    } ],
    "repeatCount": 1,
    "languageCode": "en"
  }, {
    "parts": [ {
      "text": "newspapers and magazines",
      "parameterId": "trash"
    } ],
    "repeatCount": 1,
    "languageCode": "en"
  }, {
    "parts": [ {
      "text": "food scraps",
      "parameterId": "trash"
    } ],
    "repeatCount": 1,
    "languageCode": "en"
  }, {
    "parts": [ {
      "text": "cans and bottles",
      "parameterId": "trash"
    } ],
    "repeatCount": 1,
    "languageCode": "en"
  }, {
    "parts": [ {
      "text": "pizza boxes",
      "parameterId": "trash"
    } ],
    "repeatCount": 1,
    "languageCode": "en"
  }, {
    "parts": [ {
      "text": "cardboard boxes",
      "parameterId": "trash"
    } ],
    "repeatCount": 1,
    "languageCode": "en"
  }, {
    "parts": [ {
      "text": "plastic",
      "parameterId": "trash"
    } ],
    "repeatCount": 1,
    "languageCode": "en"
  }, {
    "parts": [ {
      "text": "cartons",
      "parameterId": "trash"
    } ],
    "repeatCount": 1,
    "languageCode": "en"
  }, {
    "parts": [ {
      "text": "bin bag",
      "parameterId": "trash"
    } ],
    "repeatCount": 1,
    "languageCode": "en"
  } ]
}
